{"id":"TAB__tblProperty","name":"_tblProperty","fields":[{"name":"PropName","type":"TEXT","required":wahr,"properties":{"DefaultValue":"","ValidationRule":"","ValidationText":""}},{"name":"PropUser","type":"TEXT","required":wahr,"properties":{"DefaultValue":"\"All\"","ValidationRule":"","ValidationText":""}},{"name":"PropInhalt","type":"MEMO","required":falsch,"properties":{"DefaultValue":"","ValidationRule":"","ValidationText":""}},{"name":"Beschreibung","type":"TEXT","required":falsch,"properties":{"DefaultValue":"","ValidationRule":"","ValidationText":""}},{"name":"GueltigAb","type":"DATETIME","required":falsch,"properties":{"DefaultValue":"","ValidationRule":"","ValidationText":""}},{"name":"IstPrivat","type":"LONG","required":falsch,"properties":{"DefaultValue":"0","ValidationRule":"","ValidationText":""}},{"name":"NachschlagTyp","type":"LONG","required":falsch,"properties":{"DefaultValue":"0","ValidationRule":"","ValidationText":""}},{"name":"Erst_von","type":"TEXT","required":falsch,"properties":{"DefaultValue":"","ValidationRule":"","ValidationText":""}},{"name":"Erst_am","type":"DATETIME","required":falsch,"properties":{"DefaultValue":"","ValidationRule":"","ValidationText":""}},{"name":"Aend_von","type":"TEXT","required":falsch,"properties":{"DefaultValue":"","ValidationRule":"","ValidationText":""}},{"name":"Aend_am","type":"DATETIME","required":falsch,"properties":{"DefaultValue":"","ValidationRule":"","ValidationText":""}}],"indexes":[{"name":"PrimKey","unique":wahr,"primary":wahr,"fields":["PropName","PropUser"]}],"link":null}
