{"id":"FRM_sub_VA_Akt_Objekt_Pos","name":"sub_VA_Akt_Objekt_Pos","record_source":{"type":"table","ref":"SELECT tbl_VA_Akt_Objekt_Pos.* FROM tbl_VA_Akt_Objekt_Pos ORDER BY tbl_VA_Akt_Objekt_Pos.Sort; ","ref_id":"TAB_SELECTtbl_VA_Akt_Objekt_Pos_*FROMtbl_VA_Akt_Objekt_PosORDERBYtbl_VA_Akt_Objekt_Pos_Sort;"},"properties":{"AllowEdits":wahr,"AllowAdditions":wahr,"AllowDeletions":wahr,"DataEntry":falsch,"FilterOn":falsch,"Filter":"","OrderByOn":falsch,"OrderBy":"","Cycle":"0","NavigationButtons":falsch,"DividingLines":wahr,"DefaultView":"ContinuousForms"},"controls":[{"name":"ID","type":"TextBox","control_source":"ID","properties":{"DefaultValue":"","ValidationRule":"","ValidationText":"","Format":"","InputMask":"","Enabled":"Wahr","Locked":"Falsch","Visible":"Wahr","TabIndex":"0","TabStop":"Wahr","ForeColor":"4210752","BackColor":"16777215","BorderColor":"10921638","BorderStyle":"1","BorderWidth":"0","Left":"2835","Top":"345","Width":"9825","Height":"360"},"events":{"OnClick":{"kind":"Macro","macro":""},"OnDblClick":{"kind":"Macro","macro":""},"OnMouseDown":{"kind":"Macro","macro":""},"OnMouseUp":{"kind":"Macro","macro":""},"OnMouseMove":{"kind":"Macro","macro":""},"OnChange":{"kind":"Macro","macro":""},"OnDirty":{"kind":"Macro","macro":""},"BeforeUpdate":{"kind":"Macro","macro":""},"AfterUpdate":{"kind":"Macro","macro":""},"OnGotFocus":{"kind":"Macro","macro":""},"OnLostFocus":{"kind":"Macro","macro":""},"OnKeyDown":{"kind":"Macro","macro":""},"OnKeyUp":{"kind":"Macro","macro":""},"OnKeyPress":{"kind":"Macro","macro":""}}},{"name":"Bezeichnungsfeld0","type":"Label","properties":{"Visible":"Wahr","ForeColor":"8355711","BackColor":"16777215","BorderColor":"8355711","BorderStyle":"0","BorderWidth":"0","Left":"345","Top":"345","Width":"2428","Height":"360"},"events":{"OnClick":{"kind":"Macro","macro":""},"OnDblClick":{"kind":"Macro","macro":""},"OnMouseDown":{"kind":"Macro","macro":""},"OnMouseUp":{"kind":"Macro","macro":""},"OnMouseMove":{"kind":"Macro","macro":""},"OnChange":null,"OnDirty":null,"BeforeUpdate":null,"AfterUpdate":null,"OnGotFocus":null,"OnLostFocus":null,"OnKeyDown":null,"OnKeyUp":null,"OnKeyPress":null}},{"name":"VA_Akt_Objekt_Kopf_ID","type":"TextBox","control_source":"VA_Akt_Objekt_Kopf_ID","properties":{"DefaultValue":"","ValidationRule":"","ValidationText":"","Format":"","InputMask":"","Enabled":"Wahr","Locked":"Falsch","Visible":"Wahr","TabIndex":"1","TabStop":"Wahr","ForeColor":"4210752","BackColor":"16777215","BorderColor":"10921638","BorderStyle":"1","BorderWidth":"0","Left":"2835","Top":"885","Width":"9825","Height":"360"},"events":{"OnClick":{"kind":"Macro","macro":""},"OnDblClick":{"kind":"Macro","macro":""},"OnMouseDown":{"kind":"Macro","macro":""},"OnMouseUp":{"kind":"Macro","macro":""},"OnMouseMove":{"kind":"Macro","macro":""},"OnChange":{"kind":"Macro","macro":""},"OnDirty":{"kind":"Macro","macro":""},"BeforeUpdate":{"kind":"Macro","macro":""},"AfterUpdate":{"kind":"Macro","macro":""},"OnGotFocus":{"kind":"Macro","macro":""},"OnLostFocus":{"kind":"Macro","macro":""},"OnKeyDown":{"kind":"Macro","macro":""},"OnKeyUp":{"kind":"Macro","macro":""},"OnKeyPress":{"kind":"Macro","macro":""}}},{"name":"Bezeichnungsfeld3","type":"Label","properties":{"Visible":"Wahr","ForeColor":"0","BackColor":"16777215","BorderColor":"8355711","BorderStyle":"0","BorderWidth":"0","Left":"345","Top":"885","Width":"2428","Height":"360"},"events":{"OnClick":{"kind":"Macro","macro":""},"OnDblClick":{"kind":"Macro","macro":""},"OnMouseDown":{"kind":"Macro","macro":""},"OnMouseUp":{"kind":"Macro","macro":""},"OnMouseMove":{"kind":"Macro","macro":""},"OnChange":null,"OnDirty":null,"BeforeUpdate":null,"AfterUpdate":null,"OnGotFocus":null,"OnLostFocus":null,"OnKeyDown":null,"OnKeyUp":null,"OnKeyPress":null}},{"name":"OB_Objekt_Pos_ID","type":"TextBox","control_source":"OB_Objekt_Pos_ID","properties":{"DefaultValue":"","ValidationRule":"","ValidationText":"","Format":"","InputMask":"","Enabled":"Wahr","Locked":"Falsch","Visible":"Wahr","TabIndex":"2","TabStop":"Wahr","ForeColor":"4210752","BackColor":"16777215","BorderColor":"10921638","BorderStyle":"1","BorderWidth":"0","Left":"2835","Top":"1425","Width":"9825","Height":"360"},"events":{"OnClick":{"kind":"Macro","macro":""},"OnDblClick":{"kind":"Macro","macro":""},"OnMouseDown":{"kind":"Macro","macro":""},"OnMouseUp":{"kind":"Macro","macro":""},"OnMouseMove":{"kind":"Macro","macro":""},"OnChange":{"kind":"Macro","macro":""},"OnDirty":{"kind":"Macro","macro":""},"BeforeUpdate":{"kind":"Macro","macro":""},"AfterUpdate":{"kind":"Macro","macro":""},"OnGotFocus":{"kind":"Macro","macro":""},"OnLostFocus":{"kind":"Macro","macro":""},"OnKeyDown":{"kind":"Macro","macro":""},"OnKeyUp":{"kind":"Macro","macro":""},"OnKeyPress":{"kind":"Macro","macro":""}}},{"name":"Bezeichnungsfeld6","type":"Label","properties":{"Visible":"Wahr","ForeColor":"0","BackColor":"16777215","BorderColor":"8355711","BorderStyle":"0","BorderWidth":"0","Left":"345","Top":"1425","Width":"2428","Height":"360"},"events":{"OnClick":{"kind":"Macro","macro":""},"OnDblClick":{"kind":"Macro","macro":""},"OnMouseDown":{"kind":"Macro","macro":""},"OnMouseUp":{"kind":"Macro","macro":""},"OnMouseMove":{"kind":"Macro","macro":""},"OnChange":null,"OnDirty":null,"BeforeUpdate":null,"AfterUpdate":null,"OnGotFocus":null,"OnLostFocus":null,"OnKeyDown":null,"OnKeyUp":null,"OnKeyPress":null}},{"name":"OB_Objekt_Kopf_ID","type":"TextBox","control_source":"OB_Objekt_Kopf_ID","properties":{"DefaultValue":"","ValidationRule":"","ValidationText":"","Format":"","InputMask":"","Enabled":"Wahr","Locked":"Falsch","Visible":"Wahr","TabIndex":"3","TabStop":"Wahr","ForeColor":"4210752","BackColor":"16777215","BorderColor":"10921638","BorderStyle":"1","BorderWidth":"0","Left":"2835","Top":"1965","Width":"9825","Height":"360"},"events":{"OnClick":{"kind":"Macro","macro":""},"OnDblClick":{"kind":"Macro","macro":""},"OnMouseDown":{"kind":"Macro","macro":""},"OnMouseUp":{"kind":"Macro","macro":""},"OnMouseMove":{"kind":"Macro","macro":""},"OnChange":{"kind":"Macro","macro":""},"OnDirty":{"kind":"Macro","macro":""},"BeforeUpdate":{"kind":"Macro","macro":""},"AfterUpdate":{"kind":"Macro","macro":""},"OnGotFocus":{"kind":"Macro","macro":""},"OnLostFocus":{"kind":"Macro","macro":""},"OnKeyDown":{"kind":"Macro","macro":""},"OnKeyUp":{"kind":"Macro","macro":""},"OnKeyPress":{"kind":"Macro","macro":""}}},{"name":"Bezeichnungsfeld9","type":"Label","properties":{"Visible":"Wahr","ForeColor":"0","BackColor":"16777215","BorderColor":"8355711","BorderStyle":"0","BorderWidth":"0","Left":"345","Top":"1965","Width":"2428","Height":"360"},"events":{"OnClick":{"kind":"Macro","macro":""},"OnDblClick":{"kind":"Macro","macro":""},"OnMouseDown":{"kind":"Macro","macro":""},"OnMouseUp":{"kind":"Macro","macro":""},"OnMouseMove":{"kind":"Macro","macro":""},"OnChange":null,"OnDirty":null,"BeforeUpdate":null,"AfterUpdate":null,"OnGotFocus":null,"OnLostFocus":null,"OnKeyDown":null,"OnKeyUp":null,"OnKeyPress":null}},{"name":"Gruppe","type":"TextBox","control_source":"Gruppe","properties":{"DefaultValue":"","ValidationRule":"","ValidationText":"","Format":"","InputMask":"","Enabled":"Wahr","Locked":"Falsch","Visible":"Wahr","TabIndex":"4","TabStop":"Wahr","ForeColor":"4210752","BackColor":"16777215","BorderColor":"10921638","BorderStyle":"1","BorderWidth":"0","Left":"2835","Top":"2505","Width":"9825","Height":"360"},"events":{"OnClick":{"kind":"Macro","macro":""},"OnDblClick":{"kind":"Macro","macro":""},"OnMouseDown":{"kind":"Macro","macro":""},"OnMouseUp":{"kind":"Macro","macro":""},"OnMouseMove":{"kind":"Macro","macro":""},"OnChange":{"kind":"Macro","macro":""},"OnDirty":{"kind":"Macro","macro":""},"BeforeUpdate":{"kind":"Macro","macro":""},"AfterUpdate":{"kind":"Macro","macro":""},"OnGotFocus":{"kind":"Macro","macro":""},"OnLostFocus":{"kind":"Macro","macro":""},"OnKeyDown":{"kind":"Macro","macro":""},"OnKeyUp":{"kind":"Macro","macro":""},"OnKeyPress":{"kind":"Macro","macro":""}}},{"name":"Bezeichnungsfeld12","type":"Label","properties":{"Visible":"Wahr","ForeColor":"0","BackColor":"16777215","BorderColor":"8355711","BorderStyle":"0","BorderWidth":"0","Left":"345","Top":"2505","Width":"2428","Height":"360"},"events":{"OnClick":{"kind":"Macro","macro":""},"OnDblClick":{"kind":"Macro","macro":""},"OnMouseDown":{"kind":"Macro","macro":""},"OnMouseUp":{"kind":"Macro","macro":""},"OnMouseMove":{"kind":"Macro","macro":""},"OnChange":null,"OnDirty":null,"BeforeUpdate":null,"AfterUpdate":null,"OnGotFocus":null,"OnLostFocus":null,"OnKeyDown":null,"OnKeyUp":null,"OnKeyPress":null}},{"name":"Zusatztext","type":"TextBox","control_source":"Zusatztext","properties":{"DefaultValue":"","ValidationRule":"","ValidationText":"","Format":"","InputMask":"","Enabled":"Wahr","Locked":"Falsch","Visible":"Wahr","TabIndex":"5","TabStop":"Wahr","ForeColor":"4210752","BackColor":"16777215","BorderColor":"10921638","BorderStyle":"1","BorderWidth":"0","Left":"2835","Top":"3045","Width":"9825","Height":"360"},"events":{"OnClick":{"kind":"Macro","macro":""},"OnDblClick":{"kind":"Macro","macro":""},"OnMouseDown":{"kind":"Macro","macro":""},"OnMouseUp":{"kind":"Macro","macro":""},"OnMouseMove":{"kind":"Macro","macro":""},"OnChange":{"kind":"Macro","macro":""},"OnDirty":{"kind":"Macro","macro":""},"BeforeUpdate":{"kind":"Macro","macro":""},"AfterUpdate":{"kind":"Macro","macro":""},"OnGotFocus":{"kind":"Macro","macro":""},"OnLostFocus":{"kind":"Macro","macro":""},"OnKeyDown":{"kind":"Macro","macro":""},"OnKeyUp":{"kind":"Macro","macro":""},"OnKeyPress":{"kind":"Macro","macro":""}}},{"name":"Bezeichnungsfeld15","type":"Label","properties":{"Visible":"Wahr","ForeColor":"0","BackColor":"16777215","BorderColor":"8355711","BorderStyle":"0","BorderWidth":"0","Left":"345","Top":"3045","Width":"2428","Height":"360"},"events":{"OnClick":{"kind":"Macro","macro":""},"OnDblClick":{"kind":"Macro","macro":""},"OnMouseDown":{"kind":"Macro","macro":""},"OnMouseUp":{"kind":"Macro","macro":""},"OnMouseMove":{"kind":"Macro","macro":""},"OnChange":null,"OnDirty":null,"BeforeUpdate":null,"AfterUpdate":null,"OnGotFocus":null,"OnLostFocus":null,"OnKeyDown":null,"OnKeyUp":null,"OnKeyPress":null}},{"name":"Zusatztext2","type":"TextBox","control_source":"Zusatztext2","properties":{"DefaultValue":"","ValidationRule":"","ValidationText":"","Format":"","InputMask":"","Enabled":"Wahr","Locked":"Falsch","Visible":"Wahr","TabIndex":"7","TabStop":"Wahr","ForeColor":"4210752","BackColor":"16777215","BorderColor":"10921638","BorderStyle":"1","BorderWidth":"0","Left":"2835","Top":"3585","Width":"9825","Height":"360"},"events":{"OnClick":{"kind":"Macro","macro":""},"OnDblClick":{"kind":"Macro","macro":""},"OnMouseDown":{"kind":"Macro","macro":""},"OnMouseUp":{"kind":"Macro","macro":""},"OnMouseMove":{"kind":"Macro","macro":""},"OnChange":{"kind":"Macro","macro":""},"OnDirty":{"kind":"Macro","macro":""},"BeforeUpdate":{"kind":"Macro","macro":""},"AfterUpdate":{"kind":"Macro","macro":""},"OnGotFocus":{"kind":"Macro","macro":""},"OnLostFocus":{"kind":"Macro","macro":""},"OnKeyDown":{"kind":"Macro","macro":""},"OnKeyUp":{"kind":"Macro","macro":""},"OnKeyPress":{"kind":"Macro","macro":""}}},{"name":"Bezeichnungsfeld18","type":"Label","properties":{"Visible":"Wahr","ForeColor":"0","BackColor":"16777215","BorderColor":"8355711","BorderStyle":"0","BorderWidth":"0","Left":"345","Top":"3585","Width":"2428","Height":"360"},"events":{"OnClick":{"kind":"Macro","macro":""},"OnDblClick":{"kind":"Macro","macro":""},"OnMouseDown":{"kind":"Macro","macro":""},"OnMouseUp":{"kind":"Macro","macro":""},"OnMouseMove":{"kind":"Macro","macro":""},"OnChange":null,"OnDirty":null,"BeforeUpdate":null,"AfterUpdate":null,"OnGotFocus":null,"OnLostFocus":null,"OnKeyDown":null,"OnKeyUp":null,"OnKeyPress":null}},{"name":"Anzahl","type":"TextBox","control_source":"Anzahl","properties":{"DefaultValue":"","ValidationRule":"","ValidationText":"","Format":"","InputMask":"","Enabled":"Wahr","Locked":"Falsch","Visible":"Wahr","TabIndex":"8","TabStop":"Wahr","ForeColor":"4210752","BackColor":"16777215","BorderColor":"10921638","BorderStyle":"1","BorderWidth":"0","Left":"2835","Top":"4665","Width":"9825","Height":"360"},"events":{"OnClick":{"kind":"Macro","macro":""},"OnDblClick":{"kind":"Macro","macro":""},"OnMouseDown":{"kind":"Macro","macro":""},"OnMouseUp":{"kind":"Macro","macro":""},"OnMouseMove":{"kind":"Macro","macro":""},"OnChange":{"kind":"Macro","macro":""},"OnDirty":{"kind":"Macro","macro":""},"BeforeUpdate":{"kind":"Macro","macro":""},"AfterUpdate":{"kind":"Macro","macro":""},"OnGotFocus":{"kind":"Macro","macro":""},"OnLostFocus":{"kind":"Macro","macro":""},"OnKeyDown":{"kind":"Macro","macro":""},"OnKeyUp":{"kind":"Macro","macro":""},"OnKeyPress":{"kind":"Macro","macro":""}}},{"name":"Bezeichnungsfeld24","type":"Label","properties":{"Visible":"Wahr","ForeColor":"0","BackColor":"16777215","BorderColor":"8355711","BorderStyle":"0","BorderWidth":"0","Left":"345","Top":"4665","Width":"2428","Height":"360"},"events":{"OnClick":{"kind":"Macro","macro":""},"OnDblClick":{"kind":"Macro","macro":""},"OnMouseDown":{"kind":"Macro","macro":""},"OnMouseUp":{"kind":"Macro","macro":""},"OnMouseMove":{"kind":"Macro","macro":""},"OnChange":null,"OnDirty":null,"BeforeUpdate":null,"AfterUpdate":null,"OnGotFocus":null,"OnLostFocus":null,"OnKeyDown":null,"OnKeyUp":null,"OnKeyPress":null}},{"name":"Rel_Beginn","type":"TextBox","control_source":"Rel_Beginn","properties":{"DefaultValue":"","ValidationRule":"","ValidationText":"","Format":"","InputMask":"","Enabled":"Wahr","Locked":"Falsch","Visible":"Wahr","TabIndex":"9","TabStop":"Wahr","ForeColor":"4210752","BackColor":"16777215","BorderColor":"10921638","BorderStyle":"1","BorderWidth":"0","Left":"2835","Top":"5205","Width":"9825","Height":"360"},"events":{"OnClick":{"kind":"Macro","macro":""},"OnDblClick":{"kind":"Macro","macro":""},"OnMouseDown":{"kind":"Macro","macro":""},"OnMouseUp":{"kind":"Macro","macro":""},"OnMouseMove":{"kind":"Macro","macro":""},"OnChange":{"kind":"Macro","macro":""},"OnDirty":{"kind":"Macro","macro":""},"BeforeUpdate":{"kind":"Macro","macro":""},"AfterUpdate":{"kind":"Macro","macro":""},"OnGotFocus":{"kind":"Macro","macro":""},"OnLostFocus":{"kind":"Macro","macro":""},"OnKeyDown":{"kind":"Macro","macro":""},"OnKeyUp":{"kind":"Macro","macro":""},"OnKeyPress":{"kind":"Macro","macro":""}}},{"name":"Bezeichnungsfeld27","type":"Label","properties":{"Visible":"Wahr","ForeColor":"0","BackColor":"16777215","BorderColor":"8355711","BorderStyle":"0","BorderWidth":"0","Left":"345","Top":"5205","Width":"2428","Height":"360"},"events":{"OnClick":{"kind":"Macro","macro":""},"OnDblClick":{"kind":"Macro","macro":""},"OnMouseDown":{"kind":"Macro","macro":""},"OnMouseUp":{"kind":"Macro","macro":""},"OnMouseMove":{"kind":"Macro","macro":""},"OnChange":null,"OnDirty":null,"BeforeUpdate":null,"AfterUpdate":null,"OnGotFocus":null,"OnLostFocus":null,"OnKeyDown":null,"OnKeyUp":null,"OnKeyPress":null}},{"name":"Rel_Ende","type":"TextBox","control_source":"Rel_Ende","properties":{"DefaultValue":"","ValidationRule":"","ValidationText":"","Format":"","InputMask":"","Enabled":"Wahr","Locked":"Falsch","Visible":"Wahr","TabIndex":"10","TabStop":"Wahr","ForeColor":"4210752","BackColor":"16777215","BorderColor":"10921638","BorderStyle":"1","BorderWidth":"0","Left":"2835","Top":"5745","Width":"9825","Height":"360"},"events":{"OnClick":{"kind":"Macro","macro":""},"OnDblClick":{"kind":"Macro","macro":""},"OnMouseDown":{"kind":"Macro","macro":""},"OnMouseUp":{"kind":"Macro","macro":""},"OnMouseMove":{"kind":"Macro","macro":""},"OnChange":{"kind":"Macro","macro":""},"OnDirty":{"kind":"Macro","macro":""},"BeforeUpdate":{"kind":"Macro","macro":""},"AfterUpdate":{"kind":"Macro","macro":""},"OnGotFocus":{"kind":"Macro","macro":""},"OnLostFocus":{"kind":"Macro","macro":""},"OnKeyDown":{"kind":"Macro","macro":""},"OnKeyUp":{"kind":"Macro","macro":""},"OnKeyPress":{"kind":"Macro","macro":""}}},{"name":"Bezeichnungsfeld30","type":"Label","properties":{"Visible":"Wahr","ForeColor":"0","BackColor":"16777215","BorderColor":"8355711","BorderStyle":"0","BorderWidth":"0","Left":"345","Top":"5745","Width":"2428","Height":"360"},"events":{"OnClick":{"kind":"Macro","macro":""},"OnDblClick":{"kind":"Macro","macro":""},"OnMouseDown":{"kind":"Macro","macro":""},"OnMouseUp":{"kind":"Macro","macro":""},"OnMouseMove":{"kind":"Macro","macro":""},"OnChange":null,"OnDirty":null,"BeforeUpdate":null,"AfterUpdate":null,"OnGotFocus":null,"OnLostFocus":null,"OnKeyDown":null,"OnKeyUp":null,"OnKeyPress":null}},{"name":"Abs_Beginn","type":"TextBox","control_source":"Abs_Beginn","properties":{"DefaultValue":"","ValidationRule":"","ValidationText":"","Format":"","InputMask":"","Enabled":"Wahr","Locked":"Falsch","Visible":"Wahr","TabIndex":"11","TabStop":"Wahr","ForeColor":"4210752","BackColor":"16777215","BorderColor":"10921638","BorderStyle":"1","BorderWidth":"0","Left":"2835","Top":"6285","Width":"9825","Height":"360"},"events":{"OnClick":{"kind":"Macro","macro":""},"OnDblClick":{"kind":"Macro","macro":""},"OnMouseDown":{"kind":"Macro","macro":""},"OnMouseUp":{"kind":"Macro","macro":""},"OnMouseMove":{"kind":"Macro","macro":""},"OnChange":{"kind":"Macro","macro":""},"OnDirty":{"kind":"Macro","macro":""},"BeforeUpdate":{"kind":"Macro","macro":""},"AfterUpdate":{"kind":"Macro","macro":""},"OnGotFocus":{"kind":"Macro","macro":""},"OnLostFocus":{"kind":"Macro","macro":""},"OnKeyDown":{"kind":"Macro","macro":""},"OnKeyUp":{"kind":"Macro","macro":""},"OnKeyPress":{"kind":"Macro","macro":""}}},{"name":"Bezeichnungsfeld33","type":"Label","properties":{"Visible":"Wahr","ForeColor":"0","BackColor":"16777215","BorderColor":"8355711","BorderStyle":"0","BorderWidth":"0","Left":"345","Top":"6285","Width":"2428","Height":"360"},"events":{"OnClick":{"kind":"Macro","macro":""},"OnDblClick":{"kind":"Macro","macro":""},"OnMouseDown":{"kind":"Macro","macro":""},"OnMouseUp":{"kind":"Macro","macro":""},"OnMouseMove":{"kind":"Macro","macro":""},"OnChange":null,"OnDirty":null,"BeforeUpdate":null,"AfterUpdate":null,"OnGotFocus":null,"OnLostFocus":null,"OnKeyDown":null,"OnKeyUp":null,"OnKeyPress":null}},{"name":"Abs_Ende","type":"TextBox","control_source":"Abs_Ende","properties":{"DefaultValue":"","ValidationRule":"","ValidationText":"","Format":"","InputMask":"","Enabled":"Wahr","Locked":"Falsch","Visible":"Wahr","TabIndex":"12","TabStop":"Wahr","ForeColor":"4210752","BackColor":"16777215","BorderColor":"10921638","BorderStyle":"1","BorderWidth":"0","Left":"2835","Top":"6825","Width":"9825","Height":"360"},"events":{"OnClick":{"kind":"Macro","macro":""},"OnDblClick":{"kind":"Macro","macro":""},"OnMouseDown":{"kind":"Macro","macro":""},"OnMouseUp":{"kind":"Macro","macro":""},"OnMouseMove":{"kind":"Macro","macro":""},"OnChange":{"kind":"Macro","macro":""},"OnDirty":{"kind":"Macro","macro":""},"BeforeUpdate":{"kind":"Macro","macro":""},"AfterUpdate":{"kind":"Macro","macro":""},"OnGotFocus":{"kind":"Macro","macro":""},"OnLostFocus":{"kind":"Macro","macro":""},"OnKeyDown":{"kind":"Macro","macro":""},"OnKeyUp":{"kind":"Macro","macro":""},"OnKeyPress":{"kind":"Macro","macro":""}}},{"name":"Bezeichnungsfeld36","type":"Label","properties":{"Visible":"Wahr","ForeColor":"0","BackColor":"16777215","BorderColor":"8355711","BorderStyle":"0","BorderWidth":"0","Left":"345","Top":"6825","Width":"2428","Height":"360"},"events":{"OnClick":{"kind":"Macro","macro":""},"OnDblClick":{"kind":"Macro","macro":""},"OnMouseDown":{"kind":"Macro","macro":""},"OnMouseUp":{"kind":"Macro","macro":""},"OnMouseMove":{"kind":"Macro","macro":""},"OnChange":null,"OnDirty":null,"BeforeUpdate":null,"AfterUpdate":null,"OnGotFocus":null,"OnLostFocus":null,"OnKeyDown":null,"OnKeyUp":null,"OnKeyPress":null}},{"name":"Bemerkung","type":"TextBox","control_source":"Bemerkung","properties":{"DefaultValue":"","ValidationRule":"","ValidationText":"","Format":"","InputMask":"","Enabled":"Wahr","Locked":"Falsch","Visible":"Wahr","TabIndex":"13","TabStop":"Wahr","ForeColor":"4210752","BackColor":"16777215","BorderColor":"10921638","BorderStyle":"1","BorderWidth":"0","Left":"2835","Top":"7365","Width":"9825","Height":"360"},"events":{"OnClick":{"kind":"Macro","macro":""},"OnDblClick":{"kind":"Macro","macro":""},"OnMouseDown":{"kind":"Macro","macro":""},"OnMouseUp":{"kind":"Macro","macro":""},"OnMouseMove":{"kind":"Macro","macro":""},"OnChange":{"kind":"Macro","macro":""},"OnDirty":{"kind":"Macro","macro":""},"BeforeUpdate":{"kind":"Macro","macro":""},"AfterUpdate":{"kind":"Macro","macro":""},"OnGotFocus":{"kind":"Macro","macro":""},"OnLostFocus":{"kind":"Macro","macro":""},"OnKeyDown":{"kind":"Macro","macro":""},"OnKeyUp":{"kind":"Macro","macro":""},"OnKeyPress":{"kind":"Macro","macro":""}}},{"name":"Bezeichnungsfeld39","type":"Label","properties":{"Visible":"Wahr","ForeColor":"0","BackColor":"16777215","BorderColor":"8355711","BorderStyle":"0","BorderWidth":"0","Left":"345","Top":"7365","Width":"2428","Height":"360"},"events":{"OnClick":{"kind":"Macro","macro":""},"OnDblClick":{"kind":"Macro","macro":""},"OnMouseDown":{"kind":"Macro","macro":""},"OnMouseUp":{"kind":"Macro","macro":""},"OnMouseMove":{"kind":"Macro","macro":""},"OnChange":null,"OnDirty":null,"BeforeUpdate":null,"AfterUpdate":null,"OnGotFocus":null,"OnLostFocus":null,"OnKeyDown":null,"OnKeyUp":null,"OnKeyPress":null}},{"name":"Geschlecht","type":"ComboBox","control_source":"Geschlecht","row_source":{"type":"sql_or_table","ref":"SELECT tbl_Hlp_MA_Geschlecht.ID, tbl_Hlp_MA_Geschlecht.Geschlecht FROM tbl_Hlp_MA_Geschlecht; "},"list_props":{"ColumnCount":"2","BoundColumn":"1","ListRows":"16","ColumnWidths":"0","LimitToList":"Wahr"},"properties":{"DefaultValue":"","ValidationRule":"","ValidationText":"","Format":"","InputMask":"","Enabled":"Wahr","Locked":"Falsch","Visible":"Wahr","TabIndex":"6","TabStop":"Wahr","ForeColor":"4210752","BackColor":"16777215","BorderColor":"10921638","BorderStyle":"1","BorderWidth":"0","Left":"2835","Top":"4125","Width":"9825","Height":"359"},"events":{"OnClick":{"kind":"Macro","macro":""},"OnDblClick":{"kind":"Macro","macro":""},"OnMouseDown":{"kind":"Macro","macro":""},"OnMouseUp":{"kind":"Macro","macro":""},"OnMouseMove":{"kind":"Macro","macro":""},"OnChange":{"kind":"Macro","macro":""},"OnDirty":{"kind":"Macro","macro":""},"BeforeUpdate":{"kind":"Macro","macro":""},"AfterUpdate":{"kind":"Macro","macro":""},"OnGotFocus":{"kind":"Macro","macro":""},"OnLostFocus":{"kind":"Macro","macro":""},"OnKeyDown":{"kind":"Macro","macro":""},"OnKeyUp":{"kind":"Macro","macro":""},"OnKeyPress":{"kind":"Macro","macro":""}}},{"name":"Bezeichnungsfeld21","type":"Label","properties":{"Visible":"Wahr","ForeColor":"0","BackColor":"16777215","BorderColor":"8355711","BorderStyle":"0","BorderWidth":"0","Left":"345","Top":"4125","Width":"2428","Height":"359"},"events":{"OnClick":{"kind":"Macro","macro":""},"OnDblClick":{"kind":"Macro","macro":""},"OnMouseDown":{"kind":"Macro","macro":""},"OnMouseUp":{"kind":"Macro","macro":""},"OnMouseMove":{"kind":"Macro","macro":""},"OnChange":null,"OnDirty":null,"BeforeUpdate":null,"AfterUpdate":null,"OnGotFocus":null,"OnLostFocus":null,"OnKeyDown":null,"OnKeyUp":null,"OnKeyPress":null}},{"name":"Sort","type":"TextBox","control_source":"Sort","properties":{"DefaultValue":"","ValidationRule":"","ValidationText":"","Format":"","InputMask":"","Enabled":"Wahr","Locked":"Falsch","Visible":"Wahr","TabIndex":"14","TabStop":"Wahr","ForeColor":"4210752","BackColor":"16777215","BorderColor":"10921638","BorderStyle":"1","BorderWidth":"0","Left":"2835","Top":"7845","Width":"9825","Height":"360"},"events":{"OnClick":{"kind":"Macro","macro":""},"OnDblClick":{"kind":"Macro","macro":""},"OnMouseDown":{"kind":"Macro","macro":""},"OnMouseUp":{"kind":"Macro","macro":""},"OnMouseMove":{"kind":"Macro","macro":""},"OnChange":{"kind":"Macro","macro":""},"OnDirty":{"kind":"Macro","macro":""},"BeforeUpdate":{"kind":"Macro","macro":""},"AfterUpdate":{"kind":"Macro","macro":""},"OnGotFocus":{"kind":"Macro","macro":""},"OnLostFocus":{"kind":"Macro","macro":""},"OnKeyDown":{"kind":"Macro","macro":""},"OnKeyUp":{"kind":"Macro","macro":""},"OnKeyPress":{"kind":"Macro","macro":""}}},{"name":"Bezeichnungsfeld43","type":"Label","properties":{"Visible":"Wahr","ForeColor":"0","BackColor":"16777215","BorderColor":"8355711","BorderStyle":"0","BorderWidth":"0","Left":"345","Top":"7845","Width":"2428","Height":"360"},"events":{"OnClick":{"kind":"Macro","macro":""},"OnDblClick":{"kind":"Macro","macro":""},"OnMouseDown":{"kind":"Macro","macro":""},"OnMouseUp":{"kind":"Macro","macro":""},"OnMouseMove":{"kind":"Macro","macro":""},"OnChange":null,"OnDirty":null,"BeforeUpdate":null,"AfterUpdate":null,"OnGotFocus":null,"OnLostFocus":null,"OnKeyDown":null,"OnKeyUp":null,"OnKeyPress":null}}],"events":{"OnOpen":{"kind":"Macro","macro":""},"OnLoad":{"kind":"Macro","macro":""},"OnClose":{"kind":"Macro","macro":""},"OnCurrent":{"kind":"Macro","macro":""},"BeforeUpdate":{"kind":"Macro","macro":""},"AfterUpdate":{"kind":"Macro","macro":""},"OnError":{"kind":"Macro","macro":""},"OnTimer":{"kind":"Macro","macro":""},"OnApplyFilter":{"kind":"Macro","macro":""},"OnFilter":{"kind":"Macro","macro":""},"OnUnload":{"kind":"Macro","macro":""}}}
